aopi_index_builder/__init__.py
aopi_index_builder/context.py
aopi_index_builder/exceptions.py
aopi_index_builder/package_index.py
aopi_index_builder/plugin_manager.py
aopi_index_builder/schema.py
aopi_index_builder/utils.py
aopi_index_builder-0.1.42.dist-info/WHEEL
aopi_index_builder-0.1.42.dist-info/METADATA
aopi_index_builder-0.1.42.dist-info/RECORD
