Metadata-Version: 2.1
Name: aopi-index-builder
Version: 0.1.42
Summary: Package to build new package indices for AOPI
Author: Pavel Kirilin
Author-email: win10@list.ru
Maintainer: Pavel Kirilin
Maintainer-email: win10@list.ru
Requires-Python: >=3.9,<4.0
Classifier: Programming Language :: Python :: 3
Classifier: Programming Language :: Python :: 3.9
Requires-Dist: Jinja2 (>=2.11.2,<3.0.0)
Requires-Dist: SQLAlchemy (>=1.3.22,<2.0.0)
Requires-Dist: databases (>=0.4.1,<0.5.0)
Requires-Dist: entrypoints (>=0.3,<0.4)
Requires-Dist: fastapi (>=0.63.0,<0.64.0)
Requires-Dist: loguru (>=0.5.3,<0.6.0)
Requires-Dist: pydantic (>=1.7.3,<2.0.0)
